dldr/__init__.py
dldr/dldr.py
dldr-1.0.1.dist-info/DESCRIPTION.rst
dldr-1.0.1.dist-info/METADATA
dldr-1.0.1.dist-info/RECORD
dldr-1.0.1.dist-info/WHEEL
dldr-1.0.1.dist-info/entry_points.txt
dldr-1.0.1.dist-info/metadata.json
dldr-1.0.1.dist-info/top_level.txt
