Metadata-Version: 2.0
Name: dldr
Version: 1.0.1
Summary: Download programs from DR TV.
Home-page: https://github.com/simonbs/dldr
Author: Simon Støvring
Author-email: mail@simonbs.dk
License: MIT
Keywords: dr tv dk download danmarks radio
Platform: UNKNOWN
Classifier: Development Status :: 4 - Beta
Classifier: Intended Audience :: End Users/Desktop
Classifier: Topic :: Utilities
Classifier: License :: OSI Approved :: MIT License
Classifier: Programming Language :: Python :: 2.7
Classifier: Programming Language :: Python :: 3
Classifier: Programming Language :: Python :: 3.2
Classifier: Programming Language :: Python :: 3.3
Classifier: Programming Language :: Python :: 3.4
Classifier: Programming Language :: Python :: 3.5
Requires-Dist: docopt
Requires-Dist: schema
